src/onescounter/zerodetect.vhdl
library ieee;
use ieee.std_logic_1164.all;
use ieee.numeric_std.all;
entity zerodetect is
	port
	(
		A : in std_logic_vector(7 downto 0);
		Y : out std_logic
	);
end zerodetect;
architecture s of zerodetect is
begin
	Y <= '1' when unsigned(A) = 0 else '0';
end s;

src/onescounter/code/adder.vhdl
library ieee;
use ieee.std_logic_1164.all;
use ieee.numeric_std.all;
entity adder is
	port
	(
		A : in std_logic_vector(7 downto 0);
		B : in std_logic_vector(7 downto 0);
		Y : out std_logic_vector(7 downto 0)
	);
end adder;
architecture s of adder is
begin
	Y <= std_logic_vector(unsigned(A) + unsigned(B));
end s;

projects/01_onescounter/code/rshift.vhdl
library ieee;
use ieee.std_logic_1164.all;
entity rshift is
	port
	(
		I : in std_logic_vector(7 downto 0);
		Y : out std_logic_vector(7 downto 0)
	);
end rshift;
architecture s of rshift is
begin
	Y <= '0' & I(7 downto 1);
end s;

src/onescounter/code/mux4x8.vhdl
library ieee;
use ieee.std_logic_1164.all;
entity mux4x8 is
	port
	(
		sel : in std_logic_vector(1 downto 0);
		I0  : in std_logic_vector(7 downto 0);
		I1  : in std_logic_vector(7 downto 0);
		I2  : in std_logic_vector(7 downto 0);
		I3  : in std_logic_vector(7 downto 0);
		Y   : out std_logic_vector(7 downto 0)
	);
end mux4x8;
architecture s of mux4x8 is
begin
	with sel select
		Y <= 	I0 when "00",
		 		I1 when "01",
		 		I2 when "10",
				I3 when others;
end s;

src/onescounter/mux2x8.vhdl
library ieee;
use ieee.std_logic_1164.all;
entity mux2x8 is
	port
	(
		sel : in std_logic;
		I0  : in std_logic_vector(7 downto 0);
		I1  : in std_logic_vector(7 downto 0);
		Y   : out std_logic_vector(7 downto 0)
	);
end mux2x8;
architecture s of mux2x8 is
begin
	with sel select
	Y <= I0 when '0',
	     I1 when others;
end s;

projects/01_onescounter/code/reg8.vhdl
library ieee;
use ieee.std_logic_1164.all;
entity reg8 is
	port
	(
		CLK, rst_n : in std_logic;
		load       : in std_logic;
		D          : in std_logic_vector(7 downto 0);
		Q          : out std_logic_vector(7 downto 0)
	);
end reg8;
architecture s of reg8 is
begin
	Q <= (others => '0') when rst_n = '0' else
	     D when rising_edge(CLK) and load = '1';
end s;

src/onescounter/datapath.vhdl
library ieee;
use ieee.std_logic_1164.all;
use ieee.numeric_std.all;
-- interface
entity datapath is
	port
	(
		CLK, rst_n : in std_logic;
		-- data inputs
		X : in std_logic_vector(7 downto 0);
		-- data outputs
		OUTP : out std_logic_vector(7 downto 0);
		-- control signals
		loadA    : in std_logic;
		selA     : in std_logic;
		loadONES : in std_logic;
		selONES  : in std_logic_vector(1 downto 0);
		-- status signals
		LSB_A : out std_logic;
		zA    : out std_logic
	);
end datapath;

architecture s of datapath is
	signal A, A_in       : std_logic_vector(7 downto 0);
	signal ONES, ONES_in : std_logic_vector(7 downto 0);
	signal adder1        : std_logic_vector(ONES'range);
begin
	-- REGISTERS
	A <= (others => '0') when rst_n = '0' else
	     A_in when rising_edge(CLK) and loadA = '1';
	ONES <= (others => '0') when rst_n = '0' else
	        ONES_in when CLK'EVENT and CLK = '1' and loadONES = '1';
	-- MUX for A
	with selA select
	A_in <= X when '0',
	        '0' & A(7 downto 1) when others;
	-- MUX for ONES
	ONES_in <= (others => '0') when selONES = "00" else
				X when selONES = "10" else
	           adder1;
	-- ADDER
	adder1 <= std_logic_vector(unsigned(ONES) + 1);
	-- status signals
	LSB_A <= A(0);
	zA    <= '1' when unsigned(A) = 0 else '0';
	-- data outputs
	OUTP <= ONES;
end s;

architecture struct of datapath is
	component reg8 is
		port
		(
			CLK, rst_n : in std_logic;
			load       : in std_logic;
			D          : in std_logic_vector(7 downto 0);
			Q          : out std_logic_vector(7 downto 0)
		);
	end component;
	component mux2x8 is
		port
		(
			sel : in std_logic;
			I0  : in std_logic_vector(7 downto 0);
			I1  : in std_logic_vector(7 downto 0);
			Y   : out std_logic_vector(7 downto 0)
		);
	end component;
	component mux4x8 is
		port
		(
			sel : in std_logic_vector(1 downto 0);
			I0  : in std_logic_vector(7 downto 0);
			I1  : in std_logic_vector(7 downto 0);
			I2  : in std_logic_vector(7 downto 0);
			I3  : in std_logic_vector(7 downto 0);
			Y   : out std_logic_vector(7 downto 0)
		);
	end component;
	component rshift is
		port
		(
			I : in std_logic_vector(7 downto 0);
			Y : out std_logic_vector(7 downto 0)
		);
	end component;
	component adder is
		port
		(
			A : in std_logic_vector(7 downto 0);
			B : in std_logic_vector(7 downto 0);
			Y : out std_logic_vector(7 downto 0)
		);
	end component;
	component zerodetect is
		port
		(
			A : in std_logic_vector(7 downto 0);
			Y : out std_logic
		);
	end component;
	signal A_out, A_in       : std_logic_vector(7 downto 0);
	signal ONES_out, ONES_in : std_logic_vector(7 downto 0);
	signal adder1_out        : std_logic_vector(7 downto 0);
	signal shifter_out       : std_logic_vector(7 downto 0);
begin
	-- REGISTERS
	A : reg8
	port map(CLK, rst_n, loadA, A_in, A_out);
	ONES : reg8
	port map(CLK, rst_n, loadONES, ONES_in, ONES_out);
	-- MUX for A
	MUX_A : mux2x8
	port map(selA, X, shifter_out, A_in);

	-- MUX for ONES
	MUX_ONES : mux4x8
	port map
	(
		selONES,
		(others => '0'),
		adder1_out,
		X,
		(others => '0'),
		ONES_in
	);

	SHIFTER : rshift
	port map(A_out, shifter_out);

	-- ADDER
	ADDER1 : adder
	port map(ONES_out, "00000001", adder1_out);

	-- status signals
	LSB_A <= A_out(0);

	ZD : zerodetect
	port map(A_out, zA);

	-- data outputs
	OUTP <= ONES_out;
end struct;

src/onescounter/ctrlunit.vhdl
library ieee;
use ieee.std_logic_1164.all;

-- interface
entity ctrlunit is
	port
	(
		CLK, rst_n : in std_logic;
		-- control inputs
		DATAIN : in std_logic;
		CALC   : in std_logic;
		-- control outputs
		READY    : out std_logic;
		OK       : out std_logic;
		loadA    : out std_logic;
		selA     : out std_logic;
		loadONES : out std_logic;
		selONES  : out std_logic;
		-- status signals
		LSB_A : in std_logic;
		zA    : in std_logic
	);
end ctrlunit;

architecture behav of ctrlunit is
	type statetype is (INIT, START, INC, SHIFT, CALC_A, WAITDATA);
	signal state, nextstate : statetype;
begin
	-- FSM
	state <= INIT when rst_n = '0' else
	         nextstate when rising_edge(CLK);
	process (state, DATAIN, CALC, LSB_A, zA)
	begin
		case state is
			when INIT =>
				if CALC /= '0' then
					nextstate <= INIT;
				elsif DATAIN /= '1' then
					nextstate <= INIT;
				else
					nextstate <= START;
				end if;
			when START =>
				if LSB_A = '0' then
					nextstate <= SHIFT;
				else
					nextstate <= INC;
				end if;
			when INC =>
				if zA = '1' then
					nextstate <= WAITDATA;
				elsif LSB_A = '1' then
					nextstate <= INC;
				else
					nextstate <= SHIFT;
				end if;
			when SHIFT =>
				if zA = '1' then
					nextstate <= WAITDATA;
				elsif LSB_A = '1' then
					nextstate <= INC;
				else
					nextstate <= SHIFT;
				end if;
			when CALC_A =>
				if LSB_A = '0' then
					nextstate <= SHIFT;
				else
					nextstate <= INC;
				end if;
			when WAITDATA =>
				if CALC = '1' then
					nextstate <= INIT;
				elsif DATAIN = '0' then
					nextstate <= WAITDATA;
				else
					nextstate <= CALC_A;
				end if;
			when others =>
				nextstate <= INIT;
		end case;
	end process;

	-- OUTPUTS
	loadA <= '1' when state = INIT or
	         state = START or
	         state = INC or
	         state = SHIFT or
	         state = WAITDATA or
	         state = CALC_A else '0';
	selA <= '1' when state = START or
	        state = SHIFT or
	        state = INC or
	        state = CALC_A else '0';
	loadONES <= '1' when state = START or
	            state = INC else '0';
	selONES <= '1' when state = INC else '0';
	READY   <= '1' when state = INIT or
	         state = WAITDATA else '0';
	OK <= '1' when state = INIT else '0';
end behav;

src/onescounter/onescounter.vhdl
library ieee;
use ieee.std_logic_1164.all;
-- interface
entity onescounter is
	port
	(
		CLK, rst_n : in std_logic;
		-- data inputs
		X : in std_logic_vector(7 downto 0);
		-- data outputs
		OUTP : out std_logic_vector(7 downto 0);
		-- control inputs
		DATAIN : in std_logic;
		CALC   : in std_logic;
		-- control outputs
		READY : out std_logic;
		OK    : out std_logic
	);
end onescounter;
architecture struct of onescounter is
	component ctrlunit is
		port
		(
			CLK, rst_n : in std_logic;
			DATAIN     : in std_logic;
			CALC       : in std_logic;
			READY      : out std_logic;
			OK         : out std_logic;
			loadA      : out std_logic;
			selA       : out std_logic;
			loadONES   : out std_logic;
			selONES    : out std_logic;
			LSB_A      : in std_logic;
			zA         : in std_logic
		);
	end component;
	component datapath is
		port
		(
			CLK, rst_n : in std_logic;
			X          : in std_logic_vector(7 downto 0);
			OUTP       : out std_logic_vector(7 downto 0);
			loadA      : in std_logic;
			selA       : in std_logic;
			loadONES   : in std_logic;
			selONES    : in std_logic;
			LSB_A      : out std_logic;
			zA         : out std_logic
		);
	end component;
	signal loadA    : std_logic;
	signal selA     : std_logic;
	signal loadONES : std_logic;
	signal selONES  : std_logic;
	signal LSB_A    : std_logic;
	signal zA       : std_logic;
begin
	CTRL : ctrlunit
	port map
	(
		CLK, rst_n, DATAIN => DATAIN,
		CALC => CALC,
		OK => OK,
		selA => selA,
		selONES => selONES,
		zA => zA
	);
	DP : datapath
	port map
	(
		CLK, rst_n, X => X,
		OUTP => OUTP,
		selA => selA,
		selONES => selONES,
		zA => zA
	);
end struct;

src/onescounter/TB.vhdl
library ieee;
use ieee.std_logic_1164.all;
use ieee.numeric_std.all;
use STD.textio.all;

-- interface
entity TB is
end TB;

architecture behav of TB is
	constant CLK_SEMIPERIOD0 : time := 25 ns;
	constant CLK_SEMIPERIOD1 : time := 15 ns;
	constant CLK_PERIOD      : time :=
	CLK_SEMIPERIOD0 + CLK_SEMIPERIOD1;
	constant RESET_TIME : time := 3 * CLK_PERIOD + 9 ns;
	signal CLK, rst_n   : std_logic;
	signal count        : std_logic_vector(23 downto 0) := (others => '0');
	signal int_count    : integer := 0;
	signal start        : integer := 0;
	signal done         : integer := 0;
	signal counter_data : std_logic_vector(23 downto 0) := (others => '0');
	signal int_counter_data : integer := 0;
	signal X                : std_logic_vector(7 downto 0);
	signal OUTP             : std_logic_vector(7 downto 0);
	signal DATAIN           : std_logic := '0';
	signal CALC             : std_logic := '1';
	signal READY            : std_logic;
	signal OK               : std_logic;
	component onescounter is
		port
		(
			CLK, rst_n : in std_logic;
			X          : in std_logic_vector(7 downto 0);
			OUTP       : out std_logic_vector(7 downto 0);
			DATAIN     : in std_logic;
			CALC       : in std_logic;
			READY      : out std_logic;
			OK         : out std_logic
		);
	end component;

begin

	DUT : onescounter
	port map
	(
		CLK    => CLK, rst_n => rst_n,
		X      => X,
		OUTP   => OUTP,
		DATAIN => DATAIN,
		CALC   => CALC,
		READY  => READY,
		OK     => OK
	);

	start_process : process
	begin
		rst_n <= '1';
		wait for 1 ns;
		rst_n <= '0';
		wait for RESET_TIME;
		rst_n <= '1';
		start <= 1;
		wait;
	end process start_process;

	clk_process : process
	begin
		if CLK = '0' then
			CLK <= '1';
			wait for CLK_SEMIPERIOD1;
		else
			CLK <= '0';
			wait for CLK_SEMIPERIOD0;
			count     <= std_logic_vector(unsigned(count) + 1);
			int_count <= int_count + 1;
		end if;
	end process clk_process;

	read_file_process  : process (clk)
		file infile        : TEXT open READ_MODE is "data.txt";
		variable inputline : LINE;
		variable in_X      : bit_vector(X'range);
		variable in_DATAIN : bit;
		variable in_CALC   : bit;
	begin
		if (clk = '0') and (start = 1) and (READY = '1') then
			-- read new data from file
			if not endfile(infile) then
				readline(infile, inputline);
				read(inputline, in_X);
				X <= to_UX01(in_X);
				readline(infile, inputline);
				read(inputline, in_DATAIN);
				DATAIN <= to_UX01(in_DATAIN);
				readline(infile, inputline);
				read(inputline, in_CALC);
				CALC <= to_UX01(in_CALC);
				readline(infile, inputline);
				counter_data     <= std_logic_vector(unsigned(counter_data) + 1);
				int_counter_data <= int_counter_data + 1;
			else
				done <= 1;
			end if;
		end if;
	end process read_file_process;

	done_process        : process (done)
		variable outputline : LINE;
	begin
		if (done = 1) then
			write(outputline, string'("END simulation - "));
			write(outputline, string'("cycle counter IS "));
			write(outputline, int_count);
			writeline(output, outputline);
			assert false
			report "NONE. END OF simulation."
				severity failure;
		end if;
	end process done_process;

end behav;

src/onescounter/sim_wave.vcd
$date
	Tue Mar 25 12:21:26 2025
$end
$version
	ModelSim Version 2020.1
$end
$timescale
	1ns
$end
$scope module tb $end
$var wire 1 ! CLK $end
$var wire 1 " rst_n $end
$var wire 1 # count [23] $end
$var wire 1 $ count [22] $end
$var wire 1 % count [21] $end
$var wire 1 & count [20] $end
$var wire 1 ' count [19] $end
$var wire 1 ( count [18] $end
$var wire 1 ) count [17] $end
$var wire 1 * count [16] $end
$var wire 1 + count [15] $end
$var wire 1 , count [14] $end
$var wire 1 - count [13] $end
$var wire 1 . count [12] $end
$var wire 1 / count [11] $end
$var wire 1 0 count [10] $end
$var wire 1 1 count [9] $end
$var wire 1 2 count [8] $end
$var wire 1 3 count [7] $end
$var wire 1 4 count [6] $end
$var wire 1 5 count [5] $end
$var wire 1 6 count [4] $end
$var wire 1 7 count [3] $end
$var wire 1 8 count [2] $end
$var wire 1 9 count [1] $end
$var wire 1 : count [0] $end
$var integer 32 ; int_count $end
$var integer 32 < start $end
$var integer 32 = done $end
$var wire 1 > counter_data [23] $end
$var wire 1 ? counter_data [22] $end
$var wire 1 @ counter_data [21] $end
$var wire 1 A counter_data [20] $end
$var wire 1 B counter_data [19] $end
$var wire 1 C counter_data [18] $end
$var wire 1 D counter_data [17] $end
$var wire 1 E counter_data [16] $end
$var wire 1 F counter_data [15] $end
$var wire 1 G counter_data [14] $end
$var wire 1 H counter_data [13] $end
$var wire 1 I counter_data [12] $end
$var wire 1 J counter_data [11] $end
$var wire 1 K counter_data [10] $end
$var wire 1 L counter_data [9] $end
$var wire 1 M counter_data [8] $end
$var wire 1 N counter_data [7] $end
$var wire 1 O counter_data [6] $end
$var wire 1 P counter_data [5] $end
$var wire 1 Q counter_data [4] $end
$var wire 1 R counter_data [3] $end
$var wire 1 S counter_data [2] $end
$var wire 1 T counter_data [1] $end
$var wire 1 U counter_data [0] $end
$var integer 32 V int_counter_data $end
$var wire 1 W X [7] $end
$var wire 1 X X [6] $end
$var wire 1 Y X [5] $end
$var wire 1 Z X [4] $end
$var wire 1 [ X [3] $end
$var wire 1 \ X [2] $end
$var wire 1 ] X [1] $end
$var wire 1 ^ X [0] $end
$var wire 1 _ OUTP [7] $end
$var wire 1 ` OUTP [6] $end
$var wire 1 a OUTP [5] $end
$var wire 1 b OUTP [4] $end
$var wire 1 c OUTP [3] $end
$var wire 1 d OUTP [2] $end
$var wire 1 e OUTP [1] $end
$var wire 1 f OUTP [0] $end
$var wire 1 g DATAIN $end
$var wire 1 h CALC $end
$var wire 1 i READY $end
$var wire 1 j OK $end
$upscope $end
$enddefinitions $end
#0
0!
1"
0#
0$
0%
0&
0'
0(
0)
0*
0+
0,
0-
0.
0/
00
01
02
03
04
05
06
07
08
09
0:
b0 ;
b0 <
b0 =
0>
0?
0@
0A
0B
0C
0D
0E
0F
0G
0H
0I
0J
0K
0L
0M
0N
0O
0P
0Q
0R
0S
0T
0U
b0 V
xW
xX
xY
xZ
x[
x\
x]
x^
x_
x`
xa
xb
xc
xd
xe
xf
0g
1h
1i
1j
1i
1j
1"
0!
#1
0"
0_
0`
0a
0b
0c
0d
0e
0f
#25
1!
b1 ;
1:
#40
0!
#65
1!
b10 ;
19
0:
#80
0!
#105
1!
b11 ;
1:
#120
0!
#130
b1 <
1"
#145
1!
b100 ;
18
09
0:
#160
0!
b1 V
1U
0h
0W
0X
0Y
0Z
0[
0\
0]
0^
#185
1!
b101 ;
1:
#200
0!
b10 V
1T
0U
1g
1Z
#225
1!
b110 ;
19
0:
0j
0i
#240
0!
#265
1!
b111 ;
1:
#280
0!
#305
1!
b1000 ;
17
08
09
0:
#320
0!
#345
1!
b1001 ;
1:
#360
0!
#385
1!
b1010 ;
19
0:
#400
0!
#425
1!
b1011 ;
1:
#440
0!
#465
1!
b1100 ;
18
09
0:
1i
#480
0!
b11 V
1U
0g
0Z
1\
#505
1!
b1101 ;
1:
#520
0!
b100 V
1S
0T
0U
1g
0\
#545
1!
b1110 ;
19
0:
0i
#560
0!
#585
1!
b1111 ;
1:
#600
0!
#625
1!
b10000 ;
16
07
08
09
0:
1i
#640
0!
b101 V
1U
1W
#665
1!
b10001 ;
1:
0i
#680
0!
#705
1!
b10010 ;
19
0:
#720
0!
#745
1!
b10011 ;
1:
#760
0!
#785
1!
b10100 ;
18
09
0:
#800
0!
#825
1!
b10101 ;
1:
#840
0!
#865
1!
b10110 ;
19
0:
#880
0!
#905
1!
b10111 ;
1:
#920
0!
#945
1!
b11000 ;
17
08
09
0:
#960
0!
#985
1!
b11001 ;
1:
#1000
0!
#1025
1!
b11010 ;
19
0:
1i
#1040
0!
b110 V
1T
0U
1h
0W
1X
1Z
1\
1^
#1065
1!
b11011 ;
1:
1j
#1080
0!
b111 V
1U
#1105
1!
b11100 ;
18
09
0:
#1120
0!
b1000 V
1R
0S
0T
0U
#1145
1!
b11101 ;
1:
#1160
0!
b1001 V
1U
#1185
1!
b11110 ;
19
0:
#1200
0!
b1010 V
1T
0U
#1225
1!
b11111 ;
1:
#1240
0!
b1011 V
1U
#1265
1!
b100000 ;
15
06
07
08
09
0:
#1280
0!
b1100 V
1S
0T
0U
#1305
1!
b100001 ;
1:
#1320
0!
b1101 V
1U
#1345
1!
b100010 ;
19
0:
#1360
0!
b1110 V
1T
0U
#1385
1!
b100011 ;
1:
#1400
0!
b1111 V
1U
#1425
1!
b100100 ;
18
09
0:
#1440
0!
b10000 V
1Q
0R
0S
0T
0U
#1465
1!
b100101 ;
1:
#1480
0!
b10001 V
1U
0g
0X
0Z
0\
0^
#1505
1!
b100110 ;
19
0:
#1520
0!
b10010 V
1T
0U
#1545
1!
b100111 ;
1:
#1560
0!
b10011 V
1U
#1585
1!
b101000 ;
17
08
09
0:
#1600
0!
b10100 V
1S
0T
0U
#1625
1!
b101001 ;
1:
#1640
0!
b10101 V
1U
#1665
1!
b101010 ;
19
0:
#1680
0!
b10110 V
1T
0U
#1705
1!
b101011 ;
1:
#1720
0!
b10111 V
1U
0h
#1745
1!
b101100 ;
18
09
0:
